jwts/__init__.py
jwts/algorithms.py
jwts/claims.py
jwts/decoder.py
jwts/encoder.py
jwts/exceptions.py
jwts/helpers.py
jwts/identities.py
jwts/py.typed
jwts/utils.py
jwts-0.2.2.dist-info/METADATA
jwts-0.2.2.dist-info/WHEEL
jwts-0.2.2.dist-info/top_level.txt
jwts-0.2.2.dist-info/RECORD
