Metadata-Version: 2.1
Name: jwts
Version: 0.2.2
Summary: Set of abstractions for jwt tokens based on pyjwt[crypto].
Author: Vladimir Vojtenko
Author-email: vladimirdev635@gmail.com
License: MIT
Requires-Dist: pyjwt[crypto]
